README.md
setup.py
pycryptometer/__init__.py
pycryptometer/_cryptometer.py
pycryptometer/_indicators.py
pycryptometer/_infos.py
pycryptometer/_liquidations.py
pycryptometer/_volumes.py
pycryptometer.egg-info/PKG-INFO
pycryptometer.egg-info/SOURCES.txt
pycryptometer.egg-info/dependency_links.txt
pycryptometer.egg-info/requires.txt
pycryptometer.egg-info/top_level.txt