Metadata-Version: 2.1
Name: pycryptometer
Version: 1.3.1
Summary: API Wrapper for cryptometer.io
Home-page: https://github.com/ToasterUwU/pycryptometer
Author: ToasterUwU
Author-email: toasterger@gmail.com
License: MIT
Keywords: API-Wrapper,Cryptometer
Platform: UNKNOWN
Classifier: Programming Language :: Python :: 3
Classifier: Operating System :: OS Independent
Requires-Python: >=3.6
